COPYING
CREDITS
MANIFEST.in
README.rst
run_game.py
setup.py
last_train_to_nowhere.egg-info/PKG-INFO
last_train_to_nowhere.egg-info/SOURCES.txt
last_train_to_nowhere.egg-info/dependency_links.txt
last_train_to_nowhere.egg-info/entry_points.txt
last_train_to_nowhere.egg-info/requires.txt
last_train_to_nowhere.egg-info/top_level.txt
wildwest/__init__.py
wildwest/__main__.py
wildwest/ai.py
wildwest/game.py
wildwest/geom.py
wildwest/hud.py
wildwest/loader.py
wildwest/physics.py
wildwest/sounds.py
wildwest/spatialhash.py
wildwest/svg.py
wildwest/vector.py
wildwest/wild.py
wildwest/assets/animations/bloodspray.json
wildwest/assets/animations/crate.json
wildwest/assets/animations/horse.json
wildwest/assets/animations/lawman.json
wildwest/assets/animations/pc-horse.json
wildwest/assets/animations/pc.json
wildwest/assets/backgrounds/background.png
wildwest/assets/geometry/car.svg
wildwest/assets/geometry/crate.svg
wildwest/assets/geometry/freightcar.svg
wildwest/assets/geometry/hatch.svg
wildwest/assets/geometry/lawman-crouching.svg
wildwest/assets/geometry/lawman-standing.svg
wildwest/assets/geometry/locomotive.svg
wildwest/assets/geometry/mailcar.svg
wildwest/assets/geometry/mailsack.svg
wildwest/assets/geometry/pc-crouching.svg
wildwest/assets/geometry/table.svg
wildwest/assets/geometry/tanker.svg
wildwest/assets/levels/level1.svg
wildwest/assets/levels/level2.svg
wildwest/assets/levels/level3.svg
wildwest/assets/levels/level4.svg
wildwest/assets/levels/level5.svg
wildwest/assets/music/oh_hi_oleandro.mp3
wildwest/assets/sounds/gallop.wav
wildwest/assets/sounds/gunshot.wav
wildwest/assets/sounds/pickup.wav
wildwest/assets/sounds/thud.wav
wildwest/assets/sprites/ammo-bullet.png
wildwest/assets/sprites/ammo-revolver.png
wildwest/assets/sprites/ammo.png
wildwest/assets/sprites/bloodspray1.png
wildwest/assets/sprites/bloodspray2.png
wildwest/assets/sprites/bloodspray3.png
wildwest/assets/sprites/bloodspray4.png
wildwest/assets/sprites/cactus1.png
wildwest/assets/sprites/cactus2.png
wildwest/assets/sprites/cactus3.png
wildwest/assets/sprites/cactus4.png
wildwest/assets/sprites/car-exterior.png
wildwest/assets/sprites/car-interior.png
wildwest/assets/sprites/crate.png
wildwest/assets/sprites/freightcar-exterior.png
