Metadata-Version: 1.1
Name: last-train-to-nowhere
Version: 1.0.0
Summary: Last Train to Nowhere
Home-page: http://www.pyweek.org/e/wasabiparatha/
Author: Daniel Pope
Author-email: mauve@mauveweb.co.uk
License: UNKNOWN
Platform: UNKNOWN
Classifier: Topic :: Games/Entertainment :: Side-Scrolling/Arcade Games
Classifier: Development Status :: 5 - Production/Stable
Classifier: License :: OSI Approved :: GNU General Public License v3 (GPLv3)
Classifier: Programming Language :: Python :: 2 :: Only
Classifier: Operating System :: OS Independent
Classifier: Natural Language :: English
